Metadata-Version: 2.1
Name: textnowdemonators
Version: 0.0.1
Summary: textnow wrapper
Home-page: UNKNOWN
Author: decrypt
License: UNKNOWN
Platform: UNKNOWN
